atonix/__init__.py
atonix/actions.py
atonix/api.py
atonix/api_india.py
atonix/assets.py
atonix/auth_helper.py
atonix/issues.py
atonix/models.py
atonix/processdata.py
atonix-0.2.1.dist-info/LICENSE
atonix-0.2.1.dist-info/METADATA
atonix-0.2.1.dist-info/WHEEL
atonix-0.2.1.dist-info/top_level.txt
atonix-0.2.1.dist-info/RECORD
