Metadata-Version: 2.1
Name: atonix
Version: 0.2.1
Summary: A user friendly client to retrieve data from the AtonixOI system.
Author: Kolton Stimpert
Author-email: Kolton Stimpert <stimpertk@bv.com>
Project-URL: Homepage, https://github.com/kstimp/atonix
Project-URL: Bug Tracker, https://github.com/kstimp/atonix/issues
Platform: Python 3.8
Platform: Python 3.9
Platform: Python 3.10
Platform: Python 3.11
Classifier: Programming Language :: Python :: 3
Classifier: License :: OSI Approved :: MIT License
Classifier: Operating System :: OS Independent
Requires-Python: >=3.8
License-File: LICENSE
